LICENSE.TXT
MANIFEST.in
README.rst
setup.py
GlabTop2/__init__.py
GlabTop2/config.cfg
GlabTop2/main.py
GlabTop2/app/.DS_Store
GlabTop2/app/config_template.cfg
GlabTop2/app/environment.yml
GlabTop2/app/main.py
GlabTop2/app/run.bat
GlabTop2/app/run.sh
GlabTop2/app/images/example_csv_output.png
GlabTop2/app/images/example_ice_depths.png
GlabTop2/app/images/franz_josef.jpg
GlabTop2/test/.DS_Store
GlabTop2/test/dem25m.map
GlabTop2/test/glacid25m.map
GlabTop2/test/glaciers_rgi60.dbf
GlabTop2/test/glaciers_rgi60.prj
GlabTop2/test/glaciers_rgi60.qpj
GlabTop2/test/glaciers_rgi60.shp
GlabTop2/test/glaciers_rgi60.shx
GlabTop2_py.egg-info/PKG-INFO
GlabTop2_py.egg-info/SOURCES.txt
GlabTop2_py.egg-info/dependency_links.txt
GlabTop2_py.egg-info/requires.txt
GlabTop2_py.egg-info/top_level.txt