Metadata-Version: 2.1
Name: GlabTop2-py
Version: 2.1.0.2
Summary: GlabTop2 (Glacier bed Topography) model
Home-page: https://github.com/WilcoTerink/GlabTop2-py
Author: Wilco Terink
Author-email: terinkw@gmail.com
License: GPL-3.0
Keywords: GlabTop2 Glacier bed Topography model pcraster ice thickness distribution Randolph Glacier Inventory
Classifier: Development Status :: 5 - Production/Stable
Classifier: Intended Audience :: Science/Research
Classifier: Intended Audience :: Developers
Classifier: Intended Audience :: End Users/Desktop
Classifier: Topic :: Scientific/Engineering
Classifier: Topic :: Scientific/Engineering :: GIS
Classifier: Topic :: Scientific/Engineering :: Mathematics
Classifier: Topic :: Scientific/Engineering :: Physics
Classifier: License :: OSI Approved :: GNU General Public License v3 (GPLv3)
Classifier: Programming Language :: Python :: 3.11
Requires-Python: >=3.11
License-File: LICENSE.TXT
Requires-Dist: numpy
Requires-Dist: pandas
Requires-Dist: geopandas
Requires-Dist: scipy
Requires-Dist: streamlit
